plantdb/commons/__init__.py
plantdb/commons/db.py
plantdb/commons/io.py
plantdb/commons/log.py
plantdb/commons/sshfsdb.py
plantdb/commons/test_database.py
plantdb/commons/testing.py
plantdb/commons/utils.py
plantdb/commons/cli/__init__.py
plantdb/commons/cli/fsdb_check.py
plantdb/commons/cli/fsdb_import_file.py
plantdb/commons/cli/fsdb_import_folder.py
plantdb/commons/cli/fsdb_import_images.py
plantdb/commons/cli/shared_fsdb.py
plantdb/commons/fsdb/__init__.py
plantdb/commons/fsdb/core.py
plantdb/commons/fsdb/exceptions.py
plantdb/commons/fsdb/file_ops.py
plantdb/commons/fsdb/fsdb_tools.py
plantdb/commons/fsdb/metadata.py
plantdb/commons/fsdb/path_helpers.py
plantdb/commons/fsdb/serialization.py
plantdb/commons/fsdb/validation.py
plantdb_commons-0.14.5.dist-info/METADATA
plantdb_commons-0.14.5.dist-info/WHEEL
plantdb_commons-0.14.5.dist-info/entry_points.txt
plantdb_commons-0.14.5.dist-info/top_level.txt
plantdb_commons-0.14.5.dist-info/RECORD
