Metadata-Version: 2.4
Name: plantdb.commons
Version: 0.14.5
Summary: Core shared library for the ROMI plant database ecosystem.
Author-email: Peter Hanappe <peter.hanappe@sony.com>, Timothée Wintz <timothee@timwin.fr>, Nabil Ait Taleb <mohamednabil.aittaleb@sony.com>, Arthur Luciani <arthur.luciani@ens-lyon.fr>
Maintainer-email: Jonathan Legrand <jonathan.legrand@ens-lyon.fr>
License: LGPL-3.0-or-later
Project-URL: homepage, https://romi-project.eu/
Project-URL: documentation, https://docs.romi-project.eu/plant_imager/
Project-URL: source, https://github.com/romi/plantdb
Project-URL: issues, https://github.com/romi/plantdb/issues
Keywords: Robotics for Microfarms,ROMI,Plant Phenotyping,Scientific Database,Data Management
Classifier: Programming Language :: Python :: 3
Classifier: Development Status :: 4 - Beta
Classifier: Intended Audience :: Science/Research
Classifier: Topic :: Database
Classifier: Topic :: Scientific/Engineering :: Bio-Informatics
Classifier: Topic :: Software Development :: Libraries :: Python Modules
Classifier: Operating System :: OS Independent
Classifier: Natural Language :: English
Requires-Python: >=3.8
Requires-Dist: appdirs
Requires-Dist: bcrypt
Requires-Dist: colorlog
Requires-Dist: imagecodecs
Requires-Dist: imageio>=2.16.2
Requires-Dist: numpy
Requires-Dist: paramiko
Requires-Dist: pillow
Requires-Dist: plyfile
Requires-Dist: toml
Requires-Dist: tqdm
Provides-Extra: doc
Requires-Dist: mkdocs; extra == "doc"
Requires-Dist: mkdocs-material; extra == "doc"
Requires-Dist: mkdocstrings[python]; extra == "doc"
Requires-Dist: pymdown-extensions; extra == "doc"
Requires-Dist: markdown-exec[ansi]; extra == "doc"
Requires-Dist: mkdocs-gen-files; extra == "doc"
Requires-Dist: mkdocs-literate-nav; extra == "doc"
Requires-Dist: mkdocs-section-index; extra == "doc"
Provides-Extra: io
Requires-Dist: networkx; extra == "io"
Requires-Dist: tifffile; extra == "io"
Requires-Dist: open3d>=0.9.0.0; extra == "io"
Provides-Extra: test
Requires-Dist: nose2[coverage]; extra == "test"
Requires-Dist: coverage[toml]; extra == "test"
